{"stat.chestOpened":10,"stat.flyOneCm":20176,"stat.walkOneCm":57488,"stat.useItem.minecraft.bread":1,"stat.jump":107,"stat.playOneMinute":13631,"stat.fallOneCm":2015,"achievement.openInventory":1,"stat.leaveGame":3,"stat.damageTaken":50,"stat.damageDealt":15,"stat.furnaceInteraction":9,"stat.crouchOneCm":59,"stat.timeSinceDeath":13631,"stat.craftItem.minecraft.dye":42,"stat.mineBlock.minecraft.dirt":1,"stat.sprintOneCm":15532,"stat.useItem.minecraft.dye":42,"achievement.exploreAllBiomes":{"value":0,"progress":["Forest","Plains","Taiga"]},"stat.mineBlock.minecraft.tallgrass":5,"stat.craftingTableInteraction":2}